tablepy_lib/__init__.py
tablepy_lib/consoleFormatter.py
tablepy_lib-0.8.0.dist-info/LICENSE
tablepy_lib-0.8.0.dist-info/METADATA
tablepy_lib-0.8.0.dist-info/WHEEL
tablepy_lib-0.8.0.dist-info/RECORD
