Metadata-Version: 2.1
Name: tablepy-lib
Version: 0.8.0
Summary: This is a versatile and user-friendly Python table library that can quickly render any Dictionary{key, []} or DataFrame into a visually appealing markdown or sql insert
Author: Jordi Corbilla
Author-email: jordi.coll.corbilla@gmail.com
Requires-Python: >=3.9,<4.0
Classifier: Programming Language :: Python :: 3
Classifier: Programming Language :: Python :: 3.9
Classifier: Programming Language :: Python :: 3.10
Classifier: Programming Language :: Python :: 3.11
